simple_http_server/__init__.py
simple_http_server/__main__.py
simple_http_server/__utils.py
simple_http_server/_http_session_local_impl.py
simple_http_server/app_conf.py
simple_http_server/asgi_request_handler.py
simple_http_server/http_protocol_handler.py
simple_http_server/http_request_handler.py
simple_http_server/http_server.py
simple_http_server/logger.py
simple_http_server/routing_server.py
simple_http_server/server.py
simple_http_server/websocket_request_handler.py
simple_http_server/wsgi_request_handler.py
simple_http_server-0.24.1.dist-info/LICENSE
simple_http_server-0.24.1.dist-info/METADATA
simple_http_server-0.24.1.dist-info/WHEEL
simple_http_server-0.24.1.dist-info/top_level.txt
simple_http_server-0.24.1.dist-info/RECORD
