Metadata-Version: 2.1
Name: simple_http_server
Version: 0.24.1
Summary: This is a simple http server, use MVC like design.
Author-email: keijack <keijack.wu@gmail.com>
License: MIT License
Project-URL: homepage, https://github.com/keijack/python-simple-http-server
Project-URL: repository, https://github.com/keijack/python-simple-http-server
Keywords: http-server,websocket,http,web,web-server
Classifier: Programming Language :: Python :: 3
Classifier: License :: OSI Approved :: MIT License
Classifier: Operating System :: OS Independent
Requires-Python: >=3.7
License-File: LICENSE
Provides-Extra: test
Requires-Dist: websocket-client ; extra == 'test'
